{"version":"0.4","title":"login-features-blocks-1","type":"section","content":[{"id":"3e98b6ce","settings":{"layout":"full_width","height":"min-height","custom_height":{"unit":"px","size":925,"sizes":[]},"column_position":"stretch","structure":"21"},"elements":[{"id":"7cc34d33","settings":{"_column_size":33,"_inline_size":45.00699999999999789679350215010344982147216796875,"_inline_size_tablet":100,"_inline_size_mobile":100,"padding":{"unit":"px","top":"0","right":"0","bottom":"0","left":"0","isLinked":true}},"elements":[{"id":"751c393e","settings":{"image":{"url":"https:\/\/bdthemes.net\/demo\/ready-pages\/ready-blocks\/wp-content\/uploads\/2019\/05\/login-features2.jpg","id":51324},"image_size":"full"},"elements":[],"isInner":false,"widgetType":"image","elType":"widget"}],"isInner":false,"elType":"column"},{"id":"7f3b0d1a","settings":{"_column_size":66,"_inline_size":54.99199999999999732835931354202330112457275390625,"_inline_size_tablet":100,"_inline_size_mobile":100,"content_position":"center","background_background":"classic","background_color":"#0093ff","padding_tablet":{"unit":"px","top":"80","right":"0","bottom":"80","left":"0","isLinked":false},"padding_mobile":{"unit":"px","top":"40","right":"40","bottom":"40","left":"40","isLinked":true}},"elements":[{"id":"24f28f08","settings":{"content_width":{"unit":"px","size":350,"sizes":[]}},"elements":[{"id":"5ca6470d","settings":{"_column_size":100,"_inline_size":null,"padding":{"unit":"px","top":"0","right":"0","bottom":"0","left":"0","isLinked":true}},"elements":[{"id":"5d1e6c11","settings":{"title":"Get more things done with Loggin platform.","header_size":"h3","title_color":"#ffffff"},"elements":[],"isInner":false,"widgetType":"heading","elType":"widget"},{"id":"4f3e3e36","settings":{"editor":"<p>Access to the most powerfull tool in the entire design and web industry.<\/p>","text_color":"#ffffff"},"elements":[],"isInner":false,"widgetType":"text-editor","elType":"widget"},{"id":"26efb164","settings":{"button_text":"Log In","bdt_dropdown_dropdown_button_text":"Log In","bdt_modal_modal_button_text":"Log In","user_label":"Username or Email","user_placeholder":"Username or Email","password_label":"Password","password_placeholder":"Password","links_color":"#ffffff","links_hover_color":"#ffffff","label_color":"#ffffff","field_text_color":"#000000","field_placeholder_color":"rgba(0,0,0,0.5)","field_background_color":"#ffffff","field_border_radius":{"unit":"px","top":"3","right":"3","bottom":"3","left":"3","isLinked":true},"button_typography_typography":"custom","button_typography_font_size":{"unit":"px","size":15},"button_background_color":"#ffffff","button_border_radius":{"unit":"px","top":"3","right":"3","bottom":"3","left":"3","isLinked":true},"button_hover_color":"#ffffff","button_background_hover_color":"#59b9ff","custom_navs":[{"custom_nav_title":"Billing","icon":"fa fa-usd","custom_nav_link":{"url":"#","is_external":"","nofollow":""},"_id":"e634c85"},{"custom_nav_title":"Settings","icon":"fa fa-cog","custom_nav_link":{"url":"#","is_external":"","nofollow":""},"_id":"ca570e3"},{"custom_nav_title":"Support","icon":"fa fa-life-ring","custom_nav_link":{"url":"#","is_external":"","nofollow":""},"_id":"a7c4851"}],"show_remember_me":"","show_logged_in_message":"","logged_in_custom_message":"Hey,","button_text_color":"#000000"},"elements":[],"isInner":false,"widgetType":"bdt-user-login","elType":"widget"},{"id":"7bedcac6","settings":{"share_buttons":[{"button":"facebook","_id":"c5ebf27","text":""},{"button":"googleplus","_id":"e8f4b05","text":""},{"button":"twitter","_id":"7c37daa","text":""},{"button":"pinterest","_id":"6fa5e7f","text":""}],"view":"text","columns":"4","column_gap":{"unit":"px","size":0,"sizes":[]},"row_gap":{"unit":"px","size":0,"sizes":[]},"color_source":"custom","primary_color":"rgba(0,0,0,0)","secondary_color_hover":"#000000","_margin":{"unit":"px","top":"0","right":"0","bottom":"0","left":"-15","isLinked":false}},"elements":[],"isInner":false,"widgetType":"bdt-social-share","elType":"widget"}],"isInner":true,"elType":"column"}],"isInner":true,"elType":"section"}],"isInner":false,"elType":"column"}],"isInner":false,"elType":"section"}]}